ahwaz/Arsein.py
ahwaz/Clien.py
ahwaz/Copyright.py
ahwaz/Device.py
ahwaz/Encoder.py
ahwaz/Error.py
ahwaz/Getheader.py
ahwaz/GtM.py
ahwaz/PostData.py
ahwaz/TypeText.py
ahwaz/Zedcontent.py
ahwaz/__init__.py
Ahwaz-2.2.3.dist-info/LICENCE
Ahwaz-2.2.3.dist-info/METADATA
Ahwaz-2.2.3.dist-info/WHEEL
Ahwaz-2.2.3.dist-info/top_level.txt
Ahwaz-2.2.3.dist-info/RECORD
